__init__.py
calc_workbook.py
calc_workbook-0.1.1.dist-info/METADATA
calc_workbook-0.1.1.dist-info/WHEEL
calc_workbook-0.1.1.dist-info/top_level.txt
calc_workbook-0.1.1.dist-info/RECORD
