Metadata-Version: 2.4
Name: calc-workbook
Version: 0.1.1
Summary: Easy-to-use Python library for accessing computed Excel cell values
Author-email: Alexandre Bento Freire <devtoix@a-bentofreire.com>
Project-URL: Homepage, https://github.com/a-bentofreire/calc-workbook
Project-URL: Repository, https://github.com/a-bentofreire/calc-workbook
Project-URL: Issues, https://github.com/a-bentofreire/calc-workbook/issues
Keywords: excel,formulas,workbook,automation,calculation
Classifier: Programming Language :: Python :: 3
Classifier: Programming Language :: Python :: 3.6
Classifier: Operating System :: OS Independent
Requires-Python: >=3.6
Requires-Dist: formulas
Provides-Extra: dev
Requires-Dist: pytest; extra == "dev"
Requires-Dist: openpyxl; extra == "dev"
Requires-Dist: flake8; extra == "dev"
